invenio_s3/__init__.py
invenio_s3/config.py
invenio_s3/ext.py
invenio_s3/helpers.py
invenio_s3/multipart_client.py
invenio_s3/storage.py
invenio_s3-4.0.0.dist-info/licenses/AUTHORS.rst
invenio_s3-4.0.0.dist-info/licenses/LICENSE
invenio_s3-4.0.0.dist-info/METADATA
invenio_s3-4.0.0.dist-info/WHEEL
invenio_s3-4.0.0.dist-info/entry_points.txt
invenio_s3-4.0.0.dist-info/top_level.txt
invenio_s3-4.0.0.dist-info/RECORD
