Metadata-Version: 2.4
Name: invenio-s3
Version: 4.0.0
Summary: "S3 file storage support for Invenio. "
Home-page: https://github.com/inveniosoftware/invenio-s3
Author: Esteban J. G. Gabancho
Author-email: egabancho@gmail.com
License: MIT
Keywords: invenio s3
Platform: any
Classifier: Development Status :: 3 - Alpha
Requires-Python: >=3.7
License-File: LICENSE
License-File: AUTHORS.rst
Requires-Dist: invenio-files-rest<5.0.0,>=4.0.0
Requires-Dist: s3fs>=2025.3.2
Requires-Dist: aiobotocore<3.0.0,>=2.5.4
Provides-Extra: tests
Requires-Dist: pytest-black>=0.6.0; extra == "tests"
Requires-Dist: pytest-invenio<5.0.0,>=4.0.0; extra == "tests"
Requires-Dist: invenio-base<3.0.0,>=2.0.0; extra == "tests"
Requires-Dist: invenio-app<4.0.0,>=3.0.0; extra == "tests"
Requires-Dist: invenio-db<3.0.0,>=2.2.0; extra == "tests"
Requires-Dist: Sphinx>=4.2.0; extra == "tests"
Dynamic: license-file
